{"testCaseData":{"dividerDesc":"","orientationDesc":"","checkedButtonDesc":"","onChildViewAdded":"pass","layout_gravity":"pass","onCheckedChangeDesc":"","baselineAligned":"pass","divider":"pass","baselineAlignedChildIndexDesc":"","dividerPadding":"pass","dividerPaddingDesc":"","onChildViewAddedDesc":"","baselineAlignedChildIndex":"pass","measureWithLargestChild":"pass","orientation":"pass","measureWithLargestChildDesc":"","onChildViewRemoved":"pass","gravityDesc":"","showDividersDesc":"","checkedButton":"pass","layout_gravityDesc":"","weightSum":"pass","gravity":"pass","baselineAlignedDesc":"","layout_weightDesc":"","showDividers":"pass","layout_weight":"pass","onCheckedChange":"pass","weightSumDesc":"","onChildViewRemovedDesc":""}}