{"testCaseData":{"htmlDesc":"","iosIsOnDesc":"","paddingRight":"pass","textSizeDesc":"","maxLinesDesc":"","drawableBottom":"pass","minHeight":"pass","minWidthDesc":"","iosIsOn":"pass","text":"pass","textFormatDesc":"","drawableStart":"pass","ellipsizeDesc":"","paddingVerticalDesc":"","drawableEndDesc":"","height":"pass","maxWidth":"pass","ellipsize":"pass","firstBaselineToTopHeightDesc":"","singleLine":"pass","typeface":"pass","maxHeightDesc":"","drawableStartDesc":"","thumbTintDesc":"","switchPaddingDesc":"","shadowDxDesc":"","scrollHorizontallyDesc":"","startOrStopMarqueeDesc":"","trackTintDesc":"","paddingLeft":"pass","lastBaselineToBottomHeight":"pass","shadowDx":"pass","shadowDy":"pass","drawableRightDesc":"","checkedDesc":"","maxEms":"pass","iosHighlightedTextColor":"pass","fontFamilyDesc":"","paddingStart":"pass","drawableLeftDesc":"","maxLengthDesc":"","maxHeight":"pass","paddingEnd":"pass","paddingEndDesc":"","drawableBottomDesc":"","drawableEnd":"pass","maxWidthDesc":"","gravityDesc":"fill_horizontal, fill_vertical, fill, clip_vertical, clip_horizontal is not supported.","drawableTopDesc":"","trackTint":"pass","scrollHorizontally":"pass","minWidth":"pass","singleLineDesc":"","textFormat":"pass","justificationModeDesc":"","drawableRight":"pass","switchMinWidthDesc":"","textDesc":"","width":"pass","iosIsUserInteractionEnabled":"pass","justificationMode":"pass","iosTextColorDesc":"","typefaceDesc":"","iosOnTintColorDesc":"","textColorDesc":"","iosText":"pass","widthDesc":"","iosShadowColorDesc":"","fontFamily":"pass","paddingBottom":"pass","drawableLeft":"pass","heightDesc":"","firstBaselineToTopHeight":"pass","checked":"pass","minLinesDesc":"","paddingHorizontal":"pass","html":"pass","iosHighlightedTextColorDesc":"","paddingHorizontalDesc":"","marqueeRepeatLimit":"pass","switchPadding":"pass","iosThumbTintColorDesc":"","textColor":"pass","minLines":"pass","paddingVertical":"pass","thumbTint":"pass","lastBaselineToBottomHeightDesc":"","emsDesc":"","iosTextColor":"pass","maxLines":"pass","maxEmsDesc":"","onCheckedChange":"pass","textAllCaps":"pass","maxLength":"pass","paddingDesc":"","textStyleDesc":"","minHeightDesc":"","drawablePadding":"pass","linesDesc":"","shadowDyDesc":"","drawablePaddingDesc":"","drawableTintModeDesc":"","paddingBottomDesc":"","ems":"pass","iosIsUserInteractionEnabledDesc":"","onCheckedChangeDesc":"","minEmsDesc":"","paddingLeftDesc":"","paddingTop":"pass","lines":"pass","iosIsEnabled":"pass","iosThumbTintColor":"pass","padding":"pass","marqueeRepeatLimitDesc":"","minEms":"pass","textSize":"pass","editable":"pass","textAllCapsDesc":"","drawableTintDesc":"","editableDesc":"","iosTextDesc":"","iosIsEnabledDesc":"","iosShadowColor":"pass","drawableTop":"pass","paddingRightDesc":"","drawableTint":"pass","gravity":"quirk","iosOnTintColor":"pass","paddingStartDesc":"","drawableTintMode":"pass","textStyle":"pass","switchMinWidth":"pass","paddingTopDesc":"","startOrStopMarquee":"pass"}}